{
  "paused": false,
  "pending_cmd": null,
  "cmd_result": "✅ KRW-WLD 즉시매도 완료",
  "last_status": {
    "krw": 592632,
    "total_profit": 5345,
    "daily_pnl": 0,
    "positions": 2,
    "positions_detail": {
      "KRW-USDT": {
        "current": 1518,
        "entry_price": 1477,
        "qty": 203.11442112,
        "rate": 2.78
      },
      "KRW-SAHARA": {
        "current": 49,
        "entry_price": 50,
        "qty": 5964.21471172,
        "rate": -0.99
      }
    },
    "daily_loss": 0,
    "market_status": "normal",
    "btc_rate": -0.07419355000000001,
    "fear_greed": 12,
    "is_night": false,
    "coin_pool": [
      "KRW-BTC",
      "KRW-ETH",
      "KRW-XRP",
      "KRW-SOL",
      "KRW-USDT",
      "KRW-XLM",
      "KRW-ONDO",
      "KRW-DOGE",
      "KRW-NEAR",
      "KRW-ADA",
      "KRW-LA",
      "KRW-SUI",
      "KRW-XPL",
      "KRW-SLX",
      "KRW-ENA",
      "KRW-SAHARA",
      "KRW-BCH",
      "KRW-ARDR",
      "KRW-VIRTUAL",
      "KRW-MOVE"
    ],
    "coins": [
      "KRW-BTC",
      "KRW-ETH",
      "KRW-XRP",
      "KRW-SOL",
      "KRW-USDT",
      "KRW-XLM",
      "KRW-ONDO",
      "KRW-DOGE",
      "KRW-NEAR",
      "KRW-ADA",
      "KRW-LA",
      "KRW-SUI",
      "KRW-XPL",
      "KRW-SLX",
      "KRW-ENA",
      "KRW-SAHARA",
      "KRW-BCH",
      "KRW-ARDR",
      "KRW-VIRTUAL",
      "KRW-MOVE"
    ],
    "seed": "30만원 소액 모드"
  },
  "last_update": "18:34:34",
  "daily_loss": 0,
  "loss_date": "2026-06-06",
  "positions": {
    "KRW-USDT": {
      "entry_price": 1477.0,
      "qty": 203.11442112,
      "current": 1518.0
    },
    "KRW-SAHARA": {
      "entry_price": 50.3,
      "qty": 5964.21471172,
      "current": 49.8
    }
  },
  "peak_tracker": {
    "KRW-USDT": {
      "peak_rate": 0.035206499661475966,
      "stage": 0,
      "remain_qty": 203.1144211238998,
      "buy2_done": false,
      "buy1_price": 1477.0,
      "effective_entry": 1477.0
    },
    "KRW-SAHARA": {
      "peak_rate": 0.039761431411530816,
      "stage": 0,
      "remain_qty": 5964.214711729623,
      "buy2_done": false,
      "buy1_price": 50.3,
      "effective_entry": 50.3
    }
  }
}